catalogue/__init__.py
catalogue/catalogue.py
catalogue/compare.py
catalogue/engage.py
catalogue/parser.py
catalogue/utils.py
catalogue/version.py
repro_catalogue-1.0.0.dist-info/LICENSE
repro_catalogue-1.0.0.dist-info/METADATA
repro_catalogue-1.0.0.dist-info/WHEEL
repro_catalogue-1.0.0.dist-info/entry_points.txt
repro_catalogue-1.0.0.dist-info/top_level.txt
repro_catalogue-1.0.0.dist-info/RECORD
