Metadata-Version: 2.1
Name: repro-catalogue
Version: 1.0.0
Summary: Tool for reproducible analyses
Home-page: https://github.com/alan-turing-institute/repro-catalogue
Author: The Alan Turing Institute Research Engineering Group
Author-email: hut23@turing.ac.uk
License: MIT
Keywords: cli-tool management version-control hashing
Platform: UNKNOWN
Requires-Python: >=3.6
Requires-Dist: gitpython
